<Motion duration="120" xmlns="fl.motion.*" xmlns:geom="flash.geom.*" xmlns:filters="flash.filters.*">
	<source>
		<Source frameRate="30" x="236.5" y="417.8" scaleX="1.324" scaleY="1.372" rotation="3" elementType="movie clip" instanceName="Chest" symbolName="Chest Container">
			<dimensions>
				<geom:Rectangle left="-55.8" top="-77.75" width="111.75" height="156.85"/>
			</dimensions>
			<transformationPoint>
				<geom:Point x="0.49932885906040264" y="0.4956965253426841"/>
			</transformationPoint>
		</Source>
	</source>

	<Keyframe index="0"/>

	<Keyframe index="1" x="-5.949999999999989" y="-34" scaleX="0.9471299093655589" scaleY="0.8731778425655976" skewX="1.5" skewY="0.5"/>

	<Keyframe index="2" x="-12.400000000000006" y="-62.85000000000002" scaleX="0.9018126888217521" scaleY="0.7616618075801748" skewX="3.3" skewY="1.2999999999999998"/>

	<Keyframe index="3" x="-17.30000000000001" y="-87.10000000000002" scaleX="0.8648036253776434" scaleY="0.6639941690962099" skewX="4.8" skewY="1.7999999999999998"/>

	<Keyframe index="4" x="-17.69999999999999" y="-107.55000000000001" scaleX="0.8368580060422961" scaleY="0.5772594752186588" skewX="6.5" skewY="2.5"/>

	<Keyframe index="5" x="-17.400000000000006" y="-118.65000000000003" scaleX="0.8157099697885196" scaleY="0.5736151603498542" skewX="4.8" skewY="1.7999999999999998"/>

	<Keyframe index="6" x="-8.800000000000011" y="-127.75" scaleX="0.8036253776435045" scaleY="0.575801749271137" skewX="3" skewY="1"/>

	<Keyframe index="7" x="-4.449999999999989" y="-124.19999999999999" scaleX="0.7998489425981872" scaleY="0.5830903790087464" skewX="1.2999999999999998" skewY="0.2999999999999998"/>

	<Keyframe index="8" x="-0.8499999999999943" y="-120.35000000000002" scaleX="0.8013595166163141" scaleY="0.5947521865889212" rotation="-0.20000000000000018"/>

	<Keyframe index="9" x="7" y="-109.35000000000002" scaleX="0.8051359516616314" scaleY="0.6319241982507288" skewX="-2.7" skewY="-2"/>

	<Keyframe index="10" x="14.150000000000006" y="-91.05000000000001" scaleX="0.8111782477341389" scaleY="0.6720116618075802" skewX="-5.1" skewY="-3.5"/>

	<Keyframe index="11" x="21.350000000000023" y="-72.80000000000001" scaleX="0.816465256797583" scaleY="0.7113702623906705" skewX="-7.6" skewY="-5.3"/>

	<Keyframe index="12" x="28.350000000000023" y="-54.55000000000001" scaleX="0.8225075528700906" scaleY="0.7514577259475217" skewX="-10.2" skewY="-6.9"/>

	<Keyframe index="13" x="20.100000000000023" y="-39.94999999999999" scaleX="0.8270392749244713" scaleY="0.7798833819241983" skewX="-6.8" skewY="-4.5"/>

	<Keyframe index="14" x="11.800000000000011" y="-25.400000000000034" scaleX="0.8323262839879154" scaleY="0.8075801749271138" skewX="-3.3" skewY="-2.5"/>

	<Keyframe index="15" x="2.4000000000000057" y="-19.25" scaleX="0.8338368580060423" scaleY="0.8330903790087463" rotation="0"/>

	<Keyframe index="16" x="-3.5500000000000114" y="-30.100000000000023" scaleX="0.830060422960725" scaleY="0.7653061224489796" skewX="1.5" skewY="0.5"/>

	<Keyframe index="17" x="-9.650000000000006" y="-40.94999999999999" scaleX="0.8262839879154079" scaleY="0.6982507288629737" skewX="3.3" skewY="1.2999999999999998"/>

	<Keyframe index="18" x="-15.75" y="-55.30000000000001" scaleX="0.8194864048338368" scaleY="0.629737609329446" skewX="4.8" skewY="1.7999999999999998"/>

	<Keyframe index="19" x="-21.900000000000006" y="-69.80000000000001" scaleX="0.8134441087613292" scaleY="0.5612244897959183" skewX="6.5" skewY="2.5"/>

	<Keyframe index="20" x="-15.699999999999989" y="-78.55000000000001" scaleX="0.8074018126888217" scaleY="0.5670553935860058" skewX="4.8" skewY="1.7999999999999998"/>

	<Keyframe index="21" x="-9.550000000000011" y="-87.30000000000001" scaleX="0.8013595166163141" scaleY="0.5736151603498542" skewX="3" skewY="1"/>

	<Keyframe index="22" x="-2.5500000000000114" y="-87.80000000000001" scaleX="0.7998489425981872" scaleY="0.5830903790087464" skewX="1.2999999999999998" skewY="0.2999999999999998"/>

	<Keyframe index="23" x="0.6999999999999886" y="-84.15000000000003" scaleX="0.8013595166163141" scaleY="0.5947521865889212" rotation="-0.20000000000000018"/>

	<Keyframe index="24" x="7.599999999999994" y="-73.55000000000001" scaleX="0.8066465256797584" scaleY="0.6341107871720116" skewX="-2.7" skewY="-2"/>

	<Keyframe index="25" x="14.599999999999994" y="-62.900000000000034" scaleX="0.8119335347432023" scaleY="0.673469387755102" skewX="-5.1" skewY="-3.5"/>

	<Keyframe index="26" x="21.44999999999999" y="-52.400000000000034" scaleX="0.8172205438066465" scaleY="0.7120991253644314" skewX="-7.6" skewY="-5.1"/>

	<Keyframe index="27" x="28.350000000000023" y="-41.80000000000001" scaleX="0.8225075528700906" scaleY="0.7514577259475217" skewX="-10.2" skewY="-6.9"/>

	<Keyframe index="28" x="19.69999999999999" y="-33.19999999999999" scaleX="0.8270392749244713" scaleY="0.7798833819241983" skewX="-6.8" skewY="-4.5"/>

	<Keyframe index="29" x="11.050000000000011" y="-24.5" scaleX="0.8323262839879154" scaleY="0.8075801749271138" skewX="-3.3" skewY="-2.5"/>

	<Keyframe index="30" x="2.4000000000000057" y="-19.25" scaleX="0.8338368580060423" scaleY="0.8330903790087463" rotation="0"/>

	<Keyframe index="31" x="-3.5500000000000114" y="-30.100000000000023" scaleX="0.830060422960725" scaleY="0.7653061224489796" skewX="1.5" skewY="0.5"/>

	<Keyframe index="32" x="-9.650000000000006" y="-40.94999999999999" scaleX="0.8262839879154079" scaleY="0.6982507288629737" skewX="3.3" skewY="1.2999999999999998"/>

	<Keyframe index="33" x="-15.75" y="-55.30000000000001" scaleX="0.8194864048338368" scaleY="0.629737609329446" skewX="4.8" skewY="1.7999999999999998"/>

	<Keyframe index="34" x="-21.900000000000006" y="-69.80000000000001" scaleX="0.8134441087613292" scaleY="0.5612244897959183" skewX="6.5" skewY="2.5"/>

	<Keyframe index="35" x="-15.699999999999989" y="-78.55000000000001" scaleX="0.8074018126888217" scaleY="0.5670553935860058" skewX="4.8" skewY="1.7999999999999998"/>

	<Keyframe index="36" x="-9.550000000000011" y="-87.30000000000001" scaleX="0.8013595166163141" scaleY="0.5736151603498542" skewX="3" skewY="1"/>

	<Keyframe index="37" x="-2.5500000000000114" y="-87.80000000000001" scaleX="0.7998489425981872" scaleY="0.5830903790087464" skewX="1.2999999999999998" skewY="0.2999999999999998"/>

	<Keyframe index="38" x="0.6999999999999886" y="-84.15000000000003" scaleX="0.8013595166163141" scaleY="0.5947521865889212" rotation="-0.20000000000000018"/>

	<Keyframe index="39" x="7.599999999999994" y="-73.55000000000001" scaleX="0.8066465256797584" scaleY="0.6341107871720116" skewX="-2.7" skewY="-2"/>

	<Keyframe index="40" x="14.599999999999994" y="-62.900000000000034" scaleX="0.8119335347432023" scaleY="0.673469387755102" skewX="-5.1" skewY="-3.5"/>

	<Keyframe index="41" x="21.44999999999999" y="-52.400000000000034" scaleX="0.8172205438066465" scaleY="0.7120991253644314" skewX="-7.6" skewY="-5.1"/>

	<Keyframe index="42" x="28.350000000000023" y="-41.80000000000001" scaleX="0.8225075528700906" scaleY="0.7514577259475217" skewX="-10.2" skewY="-6.9"/>

	<Keyframe index="43" x="19.69999999999999" y="-33.19999999999999" scaleX="0.8270392749244713" scaleY="0.7798833819241983" skewX="-6.8" skewY="-4.5"/>

	<Keyframe index="44" x="11.050000000000011" y="-24.5" scaleX="0.8323262839879154" scaleY="0.8075801749271138" skewX="-3.3" skewY="-2.5"/>

	<Keyframe index="45" x="2.4000000000000057" y="-19.25" scaleX="0.8338368580060423" scaleY="0.8330903790087463" rotation="0"/>

	<Keyframe index="46" x="-3.5500000000000114" y="-30.100000000000023" scaleX="0.830060422960725" scaleY="0.7653061224489796" skewX="1.5" skewY="0.5"/>

	<Keyframe index="47" x="-9.650000000000006" y="-40.94999999999999" scaleX="0.8262839879154079" scaleY="0.6982507288629737" skewX="3.3" skewY="1.2999999999999998"/>

	<Keyframe index="48" x="-15.75" y="-55.30000000000001" scaleX="0.8194864048338368" scaleY="0.629737609329446" skewX="4.8" skewY="1.7999999999999998"/>

	<Keyframe index="49" x="-21.900000000000006" y="-69.80000000000001" scaleX="0.8134441087613292" scaleY="0.5612244897959183" skewX="6.5" skewY="2.5"/>

	<Keyframe index="50" x="-15.699999999999989" y="-78.55000000000001" scaleX="0.8074018126888217" scaleY="0.5670553935860058" skewX="4.8" skewY="1.7999999999999998"/>

	<Keyframe index="51" x="-9.550000000000011" y="-87.30000000000001" scaleX="0.8013595166163141" scaleY="0.5736151603498542" skewX="3" skewY="1"/>

	<Keyframe index="52" x="-2.5500000000000114" y="-87.80000000000001" scaleX="0.7998489425981872" scaleY="0.5830903790087464" skewX="1.2999999999999998" skewY="0.2999999999999998"/>

	<Keyframe index="53" x="0.6999999999999886" y="-84.15000000000003" scaleX="0.8013595166163141" scaleY="0.5947521865889212" rotation="-0.20000000000000018"/>

	<Keyframe index="54" x="7.599999999999994" y="-73.55000000000001" scaleX="0.8066465256797584" scaleY="0.6341107871720116" skewX="-2.7" skewY="-2"/>

	<Keyframe index="55" x="14.599999999999994" y="-62.900000000000034" scaleX="0.8119335347432023" scaleY="0.673469387755102" skewX="-5.1" skewY="-3.5"/>

	<Keyframe index="56" x="21.44999999999999" y="-52.400000000000034" scaleX="0.8172205438066465" scaleY="0.7120991253644314" skewX="-7.6" skewY="-5.1"/>

	<Keyframe index="57" x="28.350000000000023" y="-41.80000000000001" scaleX="0.8225075528700906" scaleY="0.7514577259475217" skewX="-10.2" skewY="-6.9"/>

	<Keyframe index="58" x="19.69999999999999" y="-33.19999999999999" scaleX="0.8270392749244713" scaleY="0.7798833819241983" skewX="-6.8" skewY="-4.5"/>

	<Keyframe index="59" x="11.050000000000011" y="-24.5" scaleX="0.8323262839879154" scaleY="0.8075801749271138" skewX="-3.3" skewY="-2.5"/>

	<Keyframe index="60" x="2.4000000000000057" y="-19.25" scaleX="0.8338368580060423" scaleY="0.8330903790087463" rotation="0"/>

	<Keyframe index="61" x="-3.5500000000000114" y="-30.100000000000023" scaleX="0.830060422960725" scaleY="0.7653061224489796" skewX="1.5" skewY="0.5"/>

	<Keyframe index="62" x="-9.650000000000006" y="-40.94999999999999" scaleX="0.8262839879154079" scaleY="0.6982507288629737" skewX="3.3" skewY="1.2999999999999998"/>

	<Keyframe index="63" x="-15.75" y="-55.30000000000001" scaleX="0.8194864048338368" scaleY="0.629737609329446" skewX="4.8" skewY="1.7999999999999998"/>

	<Keyframe index="64" x="-21.900000000000006" y="-69.80000000000001" scaleX="0.8134441087613292" scaleY="0.5612244897959183" skewX="6.5" skewY="2.5"/>

	<Keyframe index="65" x="-15.699999999999989" y="-78.55000000000001" scaleX="0.8074018126888217" scaleY="0.5670553935860058" skewX="4.8" skewY="1.7999999999999998"/>

	<Keyframe index="66" x="-9.550000000000011" y="-87.30000000000001" scaleX="0.8013595166163141" scaleY="0.5736151603498542" skewX="3" skewY="1"/>

	<Keyframe index="67" x="-2.5500000000000114" y="-87.80000000000001" scaleX="0.7998489425981872" scaleY="0.5830903790087464" skewX="1.2999999999999998" skewY="0.2999999999999998"/>

	<Keyframe index="68" x="0.6999999999999886" y="-84.15000000000003" scaleX="0.8013595166163141" scaleY="0.5947521865889212" rotation="-0.20000000000000018"/>

	<Keyframe index="69" x="7.599999999999994" y="-73.55000000000001" scaleX="0.8066465256797584" scaleY="0.6341107871720116" skewX="-2.7" skewY="-2"/>

	<Keyframe index="70" x="14.599999999999994" y="-62.900000000000034" scaleX="0.8119335347432023" scaleY="0.673469387755102" skewX="-5.1" skewY="-3.5"/>

	<Keyframe index="71" x="21.44999999999999" y="-52.400000000000034" scaleX="0.8172205438066465" scaleY="0.7120991253644314" skewX="-7.6" skewY="-5.1"/>

	<Keyframe index="72" x="28.350000000000023" y="-41.80000000000001" scaleX="0.8225075528700906" scaleY="0.7514577259475217" skewX="-10.2" skewY="-6.9"/>

	<Keyframe index="73" x="19.69999999999999" y="-33.19999999999999" scaleX="0.8270392749244713" scaleY="0.7798833819241983" skewX="-6.8" skewY="-4.5"/>

	<Keyframe index="74" x="11.050000000000011" y="-24.5" scaleX="0.8323262839879154" scaleY="0.8075801749271138" skewX="-3.3" skewY="-2.5"/>

	<Keyframe index="75" x="2.4000000000000057" y="-19.25" scaleX="0.8338368580060423" scaleY="0.8330903790087463" rotation="0"/>

	<Keyframe index="76" x="-3.5999999999999943" y="-29.19999999999999" scaleX="0.831570996978852" scaleY="0.7667638483965015" skewX="1.5" skewY="0.5"/>

	<Keyframe index="77" x="-9.550000000000011" y="-44.69999999999999" scaleX="0.8255287009063443" scaleY="0.6982507288629737" skewX="3.0999999999999996" skewY="1"/>

	<Keyframe index="78" x="-15.650000000000006" y="-60.19999999999999" scaleX="0.8187311178247735" scaleY="0.629008746355685" skewX="4.8" skewY="1.7999999999999998"/>

	<Keyframe index="79" x="-21.650000000000006" y="-75.80000000000001" scaleX="0.8134441087613292" scaleY="0.5612244897959183" skewX="6.5" skewY="2.5"/>

	<Keyframe index="80" x="-15.400000000000006" y="-85.30000000000001" scaleX="0.8074018126888217" scaleY="0.5670553935860058" skewX="4.8" skewY="1.7999999999999998"/>

	<Keyframe index="81" x="-9.150000000000006" y="-94.69999999999999" scaleX="0.8013595166163141" scaleY="0.5736151603498542" skewX="3" skewY="1"/>

	<Keyframe index="82" x="-2.4499999999999886" y="-97.60000000000002" scaleX="0.7998489425981872" scaleY="0.5830903790087464" skewX="1.2999999999999998" skewY="0.2999999999999998"/>

	<Keyframe index="83" x="2.6999999999999886" y="-94.44999999999999" scaleX="0.8013595166163141" scaleY="0.5947521865889212" rotation="-0.20000000000000018"/>

	<Keyframe index="84" x="8.800000000000011" y="-80.35000000000002" scaleX="0.8066465256797584" scaleY="0.6341107871720116" skewX="-2.7" skewY="-2"/>

	<Keyframe index="85" x="14.949999999999989" y="-66.25" scaleX="0.8119335347432023" scaleY="0.673469387755102" skewX="-5.1" skewY="-3.5"/>

	<Keyframe index="86" x="21.19999999999999" y="-52.10000000000002" scaleX="0.8172205438066465" scaleY="0.7120991253644314" skewX="-7.6" skewY="-5.1"/>

	<Keyframe index="87" x="27.30000000000001" y="-38.05000000000001" scaleX="0.8225075528700906" scaleY="0.7514577259475217" skewX="-10.2" skewY="-6.9"/>

	<Keyframe index="88" x="19.150000000000006" y="-26.75" scaleX="0.8270392749244713" scaleY="0.7798833819241983" skewX="-6.8" skewY="-4.5"/>

	<Keyframe index="89" x="11.050000000000011" y="-15.449999999999989" scaleX="0.8323262839879154" scaleY="0.8075801749271138" skewX="-3.3" skewY="-2.5"/>

	<Keyframe index="90" x="3.4499999999999886" y="-12.699999999999989" scaleX="0.8338368580060423" scaleY="0.8330903790087463" rotation="0"/>

	<Keyframe index="91" x="-4" y="-19.5" scaleX="0.831570996978852" scaleY="0.7667638483965015" skewX="1.5" skewY="0.5"/>

	<Keyframe index="92" x="-10" y="-37" scaleX="0.8255287009063443" scaleY="0.6982507288629737" skewX="3.0999999999999996" skewY="1"/>

	<Keyframe index="93" x="-16" y="-54.5" scaleX="0.8187311178247735" scaleY="0.629008746355685" skewX="4.8" skewY="1.7999999999999998"/>

	<Keyframe index="94" x="-21.94999999999999" y="-72" scaleX="0.8134441087613292" scaleY="0.5612244897959183" skewX="6.5" skewY="2.5"/>

	<Keyframe index="95" x="-15.699999999999989" y="-83.30000000000001" scaleX="0.8074018126888217" scaleY="0.5670553935860058" skewX="4.8" skewY="1.7999999999999998"/>

	<Keyframe index="96" x="-9.449999999999989" y="-94.60000000000002" scaleX="0.8013595166163141" scaleY="0.5736151603498542" skewX="3" skewY="1"/>

	<Keyframe index="97" x="-2.4499999999999886" y="-97.60000000000002" scaleX="0.7998489425981872" scaleY="0.5830903790087464" skewX="1.2999999999999998" skewY="0.2999999999999998"/>

	<Keyframe index="98" x="2.75" y="-94.40000000000003" scaleX="0.8013595166163141" scaleY="0.5947521865889212" rotation="-0.20000000000000018"/>

	<Keyframe index="99" x="9.199999999999989" y="-80.5" scaleX="0.8058912386706948" scaleY="0.6326530612244897" skewX="-2.7" skewY="-2"/>

	<Keyframe index="100" x="15.75" y="-66.65000000000003" scaleX="0.8104229607250755" scaleY="0.6705539358600583" skewX="-5.1" skewY="-3.5"/>

	<Keyframe index="101" x="20.80000000000001" y="-49.60000000000002" scaleX="0.816465256797583" scaleY="0.7113702623906705" skewX="-7.5" skewY="-5.1"/>

	<Keyframe index="102" x="25.80000000000001" y="-32.650000000000034" scaleX="0.8225075528700906" scaleY="0.7514577259475217" skewX="-10.2" skewY="-6.9"/>

	<Keyframe index="103" x="18.400000000000006" y="-19.25" scaleX="0.8270392749244713" scaleY="0.7798833819241983" skewX="-6.8" skewY="-4.5"/>

	<Keyframe index="104" x="11" y="-5.850000000000023" scaleX="0.8323262839879154" scaleY="0.8075801749271138" skewX="-3.3" skewY="-2.5"/>

	<Keyframe index="105" x="2.4000000000000057" y="0.6999999999999886" scaleX="0.8338368580060423" scaleY="0.8330903790087463" rotation="0"/>

	<Keyframe index="106" x="-3.8000000000000114" y="-10.75" scaleX="0.831570996978852" scaleY="0.7667638483965015" skewX="1.5" skewY="0.5"/>

	<Keyframe index="107" x="-10.050000000000011" y="-28.69999999999999" scaleX="0.8262839879154079" scaleY="0.6982507288629737" skewX="3.3" skewY="1.2999999999999998"/>

	<Keyframe index="108" x="-15.949999999999989" y="-51.400000000000034" scaleX="0.8194864048338368" scaleY="0.629737609329446" skewX="4.8" skewY="1.7999999999999998"/>

	<Keyframe index="109" x="-21.900000000000006" y="-74.05000000000001" scaleX="0.8134441087613292" scaleY="0.5612244897959183" skewX="6.5" skewY="2.5"/>

	<Keyframe index="110" x="-13.400000000000006" y="-88.60000000000002" scaleX="0.8066465256797584" scaleY="0.5670553935860058" skewX="4.8" skewY="1.7999999999999998"/>

	<Keyframe index="111" x="-10.150000000000006" y="-104.19999999999999" scaleX="0.8013595166163141" scaleY="0.5736151603498542" skewX="3" skewY="1"/>

	<Keyframe index="112" x="-2.3000000000000114" y="-106.69999999999999" scaleX="0.7998489425981872" scaleY="0.5830903790087464" skewX="1.2999999999999998" skewY="0.2999999999999998"/>

	<Keyframe index="113" x="1.9499999999999886" y="-103.85000000000002" scaleX="0.8043806646525679" scaleY="0.596938775510204" rotation="-0.20000000000000018"/>

	<Keyframe index="114" x="9.099999999999994" y="-94.35000000000002" scaleX="0.8202416918429003" scaleY="0.6443148688046647" skewX="-2.7" skewY="-2"/>

	<Keyframe index="115" x="16.19999999999999" y="-84.90000000000003" scaleX="0.8368580060422961" scaleY="0.6924198250728862" skewX="-5.1" skewY="-3.5"/>

	<Keyframe index="116" x="23.30000000000001" y="-68.90000000000003" scaleX="0.8655589123867068" scaleY="0.7529154518950436" skewX="-7.6" skewY="-5.1"/>

	<Keyframe index="117" x="26.69999999999999" y="-48.60000000000002" scaleX="0.9018126888217521" scaleY="0.8243440233236151" skewX="-10.2" skewY="-6.9"/>

	<Keyframe index="118" x="20.899999999999977" y="-28.600000000000023" scaleX="0.9471299093655589" scaleY="0.8921282798833818" skewX="-6.8" skewY="-4.5"/>

	<Keyframe index="119" x="10.449999999999989" y="-4.600000000000023" scaleX="1" scaleY="0.9708454810495627" skewX="-3.3" skewY="-2.5"/>
</Motion>